LICENSE
MANIFEST.in
README.md
requirements.txt
setup.py
futu/VERSION.txt
futu/__init__.py
futu/common/__init__.py
futu/common/callback_executor.py
futu/common/comm_add_path.py
futu/common/conn_key.txt
futu/common/conn_mng.py
futu/common/constant.py
futu/common/err.py
futu/common/ft_logger.py
futu/common/handler_context.py
futu/common/network_manager.py
futu/common/open_context_base.py
futu/common/pbjson.py
futu/common/sys_config.py
futu/common/utils.py
futu/common/pb/Common.proto
futu/common/pb/Common_pb2.py
futu/common/pb/GetDelayStatistics.proto
futu/common/pb/GetDelayStatistics_pb2.py
futu/common/pb/GetGlobalState.proto
futu/common/pb/GetGlobalState_pb2.py
futu/common/pb/GetUserInfo.proto
futu/common/pb/GetUserInfo_pb2.py
futu/common/pb/InitConnect.proto
futu/common/pb/InitConnect_pb2.py
futu/common/pb/KeepAlive.proto
futu/common/pb/KeepAlive_pb2.py
futu/common/pb/Notify.proto
futu/common/pb/Notify_pb2.py
futu/common/pb/Qot_Common.proto
futu/common/pb/Qot_Common_pb2.py
futu/common/pb/Qot_GetBasicQot.proto
futu/common/pb/Qot_GetBasicQot_pb2.py
futu/common/pb/Qot_GetBroker.proto
futu/common/pb/Qot_GetBroker_pb2.py
futu/common/pb/Qot_GetCapitalDistribution.proto
futu/common/pb/Qot_GetCapitalDistribution_pb2.py
futu/common/pb/Qot_GetCapitalFlow.proto
futu/common/pb/Qot_GetCapitalFlow_pb2.py
futu/common/pb/Qot_GetCodeChange.proto
futu/common/pb/Qot_GetCodeChange_pb2.py
futu/common/pb/Qot_GetFutureInfo.proto
futu/common/pb/Qot_GetFutureInfo_pb2.py
futu/common/pb/Qot_GetHistoryKL.proto
futu/common/pb/Qot_GetHistoryKLPoints.proto
futu/common/pb/Qot_GetHistoryKLPoints_pb2.py
futu/common/pb/Qot_GetHistoryKL_pb2.py
futu/common/pb/Qot_GetHoldingChangeList.proto
futu/common/pb/Qot_GetHoldingChangeList_pb2.py
futu/common/pb/Qot_GetIpoList.proto
futu/common/pb/Qot_GetIpoList_pb2.py
futu/common/pb/Qot_GetKL.proto
futu/common/pb/Qot_GetKL_pb2.py
futu/common/pb/Qot_GetMarketState.proto
futu/common/pb/Qot_GetMarketState_pb2.py
futu/common/pb/Qot_GetOptionChain.proto
futu_api.egg-info/PKG-INFO
futu_api.egg-info/SOURCES.txt
futu_api.egg-info/dependency_links.txt
futu_api.egg-info/requires.txt
futu_api.egg-info/top_level.txt