Metadata-Version: 2.1
Name: futu-api
Version: 9.4.5408
Summary: Futu Quantitative Trading API
Home-page: https://github.com/FutunnOpen/py-futu-api
Author: Futu, Inc.
Author-email: ftdev@futunn.com
License: Apache License 2.0
Keywords: Futu HK/US Stock Quant Trading API
License-File: LICENSE
